__init__.py
my_prj_name/__init__.py
my_prj_name/azure_key_vault.py
my_prj_name/helloworld.py
my_prj_name/version.py
mypackage_sdm-0.0.2.dist-info/LICENSE
mypackage_sdm-0.0.2.dist-info/METADATA
mypackage_sdm-0.0.2.dist-info/WHEEL
mypackage_sdm-0.0.2.dist-info/top_level.txt
mypackage_sdm-0.0.2.dist-info/RECORD
