Metadata-Version: 2.1
Name: mypackage-sdm
Version: 0.0.2
Summary: This project is for testing purposes
Author: Samuel Demir
Author-email: demir.samuel@outlook.de
License: MIT
Platform: any
Classifier: Programming Language :: Python :: 3
Classifier: License :: OSI Approved :: MIT License
Classifier: Operating System :: OS Independent
Requires-Python: >=3.8
License-File: LICENSE
Requires-Dist: requests
Requires-Dist: importlib-metadata ; python_version == "3.8"
